setup.cfg
setup.py
py_transcend.egg-info/PKG-INFO
py_transcend.egg-info/SOURCES.txt
py_transcend.egg-info/dependency_links.txt
py_transcend.egg-info/top_level.txt
transcend/__init__.py
transcend/misc.py
transcend/user.py
transcend/services/__init__.py
transcend/services/data_service.py
transcend/services/facebook.py
transcend/services/fitbit.py
transcend/services/instagram.py
transcend/services/linkedin.py
transcend/services/moves.py
transcend/services/reddit.py
transcend/services/rescuetime.py
transcend/services/spotify.py
transcend/services/twitter.py
transcend/services/underarmour.py
transcend/services/youtube.py