Metadata-Version: 1.0
Name: py-transcend
Version: 0.0.9
Summary: Python utilties for managing Transcend data.
Home-page: https://github.com/transcend-inc/py-transcend
Author: Michael Farrell
Author-email: mike@transcendbeta.com
License: MIT
Platform: UNKNOWN
